ez_setup.py
setup.py
Colubrid.egg-info/PKG-INFO
Colubrid.egg-info/SOURCES.txt
Colubrid.egg-info/dependency_links.txt
Colubrid.egg-info/top_level.txt
colubrid/__init__.py
colubrid/application.py
colubrid/const.py
colubrid/debug.py
colubrid/exceptions.py
colubrid/reloader.py
colubrid/request.py
colubrid/response.py
colubrid/server.py
colubrid/utils.py
examples/__init__.py
examples/customapp.py
examples/dynamicresponse.py
examples/helloworld.py
examples/objectapplication.py
examples/uploaddemo.py
examples/webpylike.py
examples/resolv/__init__.py
examples/resolv/application.py
examples/resolv/apps/__init__.py
examples/resolv/apps/app_test.py
examples/static/test.txt
examples/wiki/wiki.py
examples/wiki/shared/screen.css
