Metadata-Version: 1.0
Name: Colubrid
Version: 0.10
Summary: simple wsgi publisher
Home-page: http://wsgiarea.pocoo.org/colubrid/
Author: Armin Ronacher
Author-email: armin.ronacher@active-4.com
License: BSD License
Download-URL: http://wsgiarea.pocoo.org/colubrid/dist/Colubrid-0.10.tar.gz
Keywords: wsgi web
Platform: any
Classifier: Development Status :: 5 - Production/Stable
Classifier: Environment :: Web Environment
Classifier: License :: OSI Approved :: BSD License
Classifier: Operating System :: OS Independent
Classifier: Programming Language :: Python
Classifier: Topic :: Internet :: WWW/HTTP
Classifier: Topic :: Internet :: WWW/HTTP :: Dynamic Content
